{"last_close_date":"2022-01-18","last_close_price":4585.82,"pred_date":"2022-01-18","pred_time":"2022-01-18 13:58:15","max_days_auto_prices":"4585.82|4662.85|4659.03|4726.35","dat_rows":10592,"pred_up":0.5581,"pred_up_prcnt":0.6285,"cond_cnt":72,"all_cnt":129,"low_conf_90":0.4819,"cond":"up_dn_dn_dn_dn$","min_chng":-3,"max_chng":-2,"days_checked":4,"pred_up_sign":0.5454,"pred_up_prcnt_sign":0.609,"cond_cnt_sign":487,"all_cnt_sign":893,"low_conf_90_sign":0.5173,"cond_sign":"up_dn$","cond_prices_sign":{},"min_chng_sign":-2,"max_chng_sign":-1,"days_checked_sign":4,"fear_greed":52}
