{"last_close_date":"2022-03-16","last_close_price":4314.47,"pred_date":"2022-03-16","pred_time":"2022-03-16 14:56:26","max_days_auto_prices":"4314.47|4262.45|4173.11|4204.31","dat_rows":10632,"pred_up":0.4771,"pred_up_prcnt":0.338,"cond_cnt":125,"all_cnt":262,"low_conf_90":0.4248,"cond":"up_up_up_up_up$","min_chng":1,"max_chng":2,"days_checked":4,"pred_up_sign":0.4419,"pred_up_prcnt_sign":0.708,"cond_cnt_sign":57,"all_cnt_sign":129,"low_conf_90_sign":0.3677,"cond_sign":"up_up_up$","cond_prices_sign":{},"min_chng_sign":3,"max_chng_sign":4,"days_checked_sign":4,"fear_greed":18}
