[{"date":"2024-01-22","rsi":68.81,"close":4850.43,"close_target":4801.93,"close_target_3":4704.92,"close_target_5":4607.91},{"date":"2024-01-23","rsi":70.15,"close":4864.6,"close_target":4815.95,"close_target_3":4718.66,"close_target_5":4621.37},{"date":"2024-01-24","rsi":70.53,"close":4868.55,"close_target":4819.86,"close_target_3":4722.49,"close_target_5":4625.12},{"date":"2024-01-25","rsi":72.93,"close":4894.16,"close_target":4845.22,"close_target_3":4747.34,"close_target_5":4649.45,"diff_gain_70":-1,"rsi_target":62.44,"rsi_target_3":48.5,"rsi_target_5":39.64}]
