{"run_time":"2024-01-31 02:56:21","date":"2024-01-30","result_df":[{"symbol":"AGG","close":98.65,"close_date":"2024-01-30"},{"symbol":"VTI","close":243.98,"close_date":"2024-01-30"},{"symbol":"%5EVIX","close":13.31,"close_date":"2024-01-30"},{"symbol":"SPXL","close":113.14,"close_date":"2024-01-30"},{"symbol":"SPXU","close":7.9,"close_date":"2024-01-30"},{"symbol":"SSO","close":68.92,"close_date":"2024-01-30"},{"symbol":"SPUU","close":109.42,"close_date":"2024-01-30"},{"symbol":"SDS","close":28.3,"close_date":"2024-01-30"},{"symbol":"MUB","close":108.16,"close_date":"2024-01-30"},{"symbol":"SPLB","close":23.55,"close_date":"2024-01-30"},{"symbol":"SPTL","close":28.22,"close_date":"2024-01-30"},{"symbol":"VNQ","close":84.7,"close_date":"2024-01-30"},{"symbol":"USRT","close":52.51,"close_date":"2024-01-30"},{"symbol":"QQQ","close":425.3,"close_date":"2024-01-30"},{"symbol":"IPO","close":34.74,"close_date":"2024-01-30"},{"symbol":"LGLV","close":148.1,"close_date":"2024-01-30"},{"symbol":"IVV","close":493.3,"close_date":"2024-01-30"},{"symbol":"VINIX","close":406.61,"close_date":"2024-01-30"},{"symbol":"VIIIX","close":406.61,"close_date":"2024-01-30"},{"symbol":"FXAIX","close":171.02,"close_date":"2024-01-30"},{"symbol":"TIEIX","close":34.63,"close_date":"2024-01-30"},{"symbol":"VSMPX","close":222.8,"close_date":"2024-01-30"},{"symbol":"VBTLX","close":9.61,"close_date":"2024-01-30"},{"symbol":"VBTIX","close":9.61,"close_date":"2024-01-30"},{"symbol":"SPTM","close":60.15,"close_date":"2024-01-30"},{"symbol":"STIP","close":98.82,"close_date":"2024-01-30"},{"symbol":"SPAB","close":25.48,"close_date":"2024-01-30"},{"symbol":"SSSYX","close":368.62,"close_date":"2024-01-30"},{"symbol":"GBTC","close":38.87,"close_date":"2024-01-30"},{"symbol":"VFIAX","close":454.67,"close_date":"2024-01-30"}]}
