{"run_time":"2024-06-08 03:56:29","date":"2024-06-07","result_df":[{"symbol":"AGG","close":96.62,"close_date":"2024-06-07"},{"symbol":"VTI","close":262.95,"close_date":"2024-06-07"},{"symbol":"%5EVIX","close":12.22,"close_date":"2024-06-07"},{"symbol":"SPXL","close":137.97,"close_date":"2024-06-07"},{"symbol":"SPXU","close":31.1,"close_date":"2024-06-07"},{"symbol":"SSO","close":79.53,"close_date":"2024-06-07"},{"symbol":"SPUU","close":126.65,"close_date":"2024-06-07"},{"symbol":"SDS","close":24.36,"close_date":"2024-06-07"},{"symbol":"MUB","close":106.16,"close_date":"2024-06-07"},{"symbol":"SPLB","close":22.63,"close_date":"2024-06-07"},{"symbol":"SPTL","close":27.1,"close_date":"2024-06-07"},{"symbol":"VNQ","close":82.96,"close_date":"2024-06-07"},{"symbol":"USRT","close":52.35,"close_date":"2024-06-07"},{"symbol":"QQQ","close":462.96,"close_date":"2024-06-07"},{"symbol":"IPO","close":39.43,"close_date":"2024-06-07"},{"symbol":"LGLV","close":152.95,"close_date":"2024-06-07"},{"symbol":"IVV","close":536.73,"close_date":"2024-06-07"},{"symbol":"VINIX","close":441.14,"close_date":"2024-06-07"},{"symbol":"VIIIX","close":441.14,"close_date":"2024-06-07"},{"symbol":"FXAIX","close":186.1,"close_date":"2024-06-07"},{"symbol":"TIEIX","close":37.44,"close_date":"2024-06-07"},{"symbol":"VSMPX","close":240.12,"close_date":"2024-06-07"},{"symbol":"VBTLX","close":9.45,"close_date":"2024-06-07"},{"symbol":"VBTIX","close":9.45,"close_date":"2024-06-07"},{"symbol":"SPTM","close":65.19,"close_date":"2024-06-07"},{"symbol":"STIP","close":98.87,"close_date":"2024-06-07"},{"symbol":"SPAB","close":24.95,"close_date":"2024-06-07"},{"symbol":"SSSYX","close":402.39,"close_date":"2024-06-07"},{"symbol":"GBTC","close":61.48,"close_date":"2024-06-07"},{"symbol":"VFIAX","close":494.66,"close_date":"2024-06-07"}]}
