{"run_time":"2024-04-05 03:56:26","date":"2024-04-04","result_df":[{"symbol":"AGG","close":97.16,"close_date":"2024-04-04"},{"symbol":"VTI","close":254.61,"close_date":"2024-04-04"},{"symbol":"%5EVIX","close_date":"2024-04-04"},{"symbol":"SPXL","close":126.18,"close_date":"2024-04-04"},{"symbol":"SPXU","close":6.87,"close_date":"2024-04-04"},{"symbol":"SSO","close":74.45,"close_date":"2024-04-04"},{"symbol":"SPUU","close":118.48,"close_date":"2024-04-04"},{"symbol":"SDS","close":25.89,"close_date":"2024-04-04"},{"symbol":"MUB","close":106.85,"close_date":"2024-04-04"},{"symbol":"SPLB","close":22.78,"close_date":"2024-04-04"},{"symbol":"SPTL","close":27.4,"close_date":"2024-04-04"},{"symbol":"VNQ","close":83.51,"close_date":"2024-04-04"},{"symbol":"USRT","close":51.95,"close_date":"2024-04-04"},{"symbol":"QQQ","close":435.34,"close_date":"2024-04-04"},{"symbol":"IPO","close":40.02,"close_date":"2024-04-04"},{"symbol":"LGLV","close":152.23,"close_date":"2024-04-04"},{"symbol":"IVV","close":515.61,"close_date":"2024-04-04"},{"symbol":"VINIX","close_date":"2024-04-04"},{"symbol":"VIIIX","close_date":"2024-04-04"},{"symbol":"FXAIX","close_date":"2024-04-04"},{"symbol":"TIEIX","close_date":"2024-04-04"},{"symbol":"VSMPX","close_date":"2024-04-04"},{"symbol":"VBTLX","close_date":"2024-04-04"},{"symbol":"VBTIX","close_date":"2024-04-04"},{"symbol":"SPTM","close":62.9,"close_date":"2024-04-04"},{"symbol":"STIP","close":99.49,"close_date":"2024-04-04"},{"symbol":"SPAB","close":25.08,"close_date":"2024-04-04"},{"symbol":"SSSYX","close_date":"2024-04-04"},{"symbol":"GBTC","close":61.04,"close_date":"2024-04-04"},{"symbol":"VFIAX","close_date":"2024-04-04"}]}
