{"run_time":"2022-09-26 15:02:55","date":"2022-09-26","hi_rsi":65,"lo_rsi":43,"sp500_mean":45.52,"sp500_sd":11.49,"sp500_last":28.1,"result_str":"SPY:28.1_AGG:19.7_GBTC:38.8_BITO:42.5_SPBC:28.6_IPO:32.5_MUB:20_QQQ:30.6_RJA:39.7_PDBC:29.3_SSO:28.2_SFYF:30.3_TIP:16.6_USRT:19.2_VTI:27.5_VXUS:22.2_VT:24.7_BNDW:20.8_RLY:23.6_AOK:19.5_AOA:24.8_2022-09-26","result_df":[{"symbol":"AGG","rsi":19.7,"close":97.2,"close_date":"2022-09-23"},{"symbol":"AOA","rsi":24.8,"close":56.66,"close_date":"2022-09-23"},{"symbol":"AOK","rsi":19.5,"close":33.05,"close_date":"2022-09-23"},{"symbol":"BITO","rsi":42.5,"close":11.55,"close_date":"2022-09-23"},{"symbol":"BNDW","rsi":20.8,"close":67.55,"close_date":"2022-09-23"},{"symbol":"GBTC","rsi":38.8,"close":11.2,"close_date":"2022-09-23"},{"symbol":"IPO","rsi":32.5,"close":28.36,"close_date":"2022-09-23"},{"symbol":"MUB","rsi":20,"close":103.36,"close_date":"2022-09-23"},{"symbol":"PDBC","rsi":29.3,"close":16.22,"close_date":"2022-09-23"},{"symbol":"QQQ","rsi":30.6,"close":275.51,"close_date":"2022-09-23"},{"symbol":"RJA","rsi":39.7,"close":9.19,"close_date":"2022-09-23"},{"symbol":"RLY","rsi":23.6,"close":26.2,"close_date":"2022-09-23"},{"symbol":"SFYF","rsi":30.3,"close":22.93,"close_date":"2022-09-23"},{"symbol":"SPBC","rsi":28.6,"close":19.8,"close_date":"2022-09-23"},{"symbol":"SPY","rsi":28.1,"close":367.95,"close_date":"2022-09-23"},{"symbol":"SSO","rsi":28.2,"close":42.23,"close_date":"2022-09-23"},{"symbol":"TIP","rsi":16.6,"close":107.54,"close_date":"2022-09-23"},{"symbol":"USRT","rsi":19.2,"close":49.93,"close_date":"2022-09-23"},{"symbol":"VT","rsi":24.7,"close":80.83,"close_date":"2022-09-23"},{"symbol":"VTI","rsi":27.5,"close":184.26,"close_date":"2022-09-23"},{"symbol":"VXUS","rsi":22.2,"close":46.69,"close_date":"2022-09-23"}]}
