{"run_time":"2023-01-13 13:52:59","date":"2023-01-13","hi_rsi":65,"lo_rsi":43,"sp500_mean":46.76,"sp500_sd":10.94,"sp500_last":59.4,"result_str":"GBTC:76.3_BITO:76.6_MUB:72.7_VXUS:70.1_AOA:65.8_2023-01-13","result_df":[{"symbol":"AOA","rsi":65.8,"close":62.71,"close_date":"2023-01-12"},{"symbol":"BITO","rsi":76.6,"close":12.1,"close_date":"2023-01-12"},{"symbol":"GBTC","rsi":76.3,"close":10.49,"close_date":"2023-01-12"},{"symbol":"MUB","rsi":72.7,"close":107.7,"close_date":"2023-01-12"},{"symbol":"VXUS","rsi":70.1,"close":55.23,"close_date":"2023-01-12"}]}
