{"run_time":"2022-08-15 14:57:37","date":"2022-08-15","hi_rsi":65,"lo_rsi":43,"result_str":"SPBC:74.7_IPO:66_QQQ:74.9_SSO:81_SFYF:72.3_USRT:85.7_VTI:81.7_VXUS:69.1_VT:79_RLY:68.1_AOK:71.4_AOA:78.5_2022-08-15","result_df":[{"symbol":"AOA","rsi":78.5,"close":64.46,"close_date":"2022-08-12"},{"symbol":"AOK","rsi":71.4,"close":35.88,"close_date":"2022-08-12"},{"symbol":"IPO","rsi":66,"close":36.45,"close_date":"2022-08-12"},{"symbol":"QQQ","rsi":74.9,"close":330.39,"close_date":"2022-08-12"},{"symbol":"RLY","rsi":68.1,"close":29.35,"close_date":"2022-08-12"},{"symbol":"SFYF","rsi":72.3,"close":28.86,"close_date":"2022-08-12"},{"symbol":"SPBC","rsi":74.7,"close":23.61,"close_date":"2022-08-12"},{"symbol":"SSO","rsi":81,"close":57.09,"close_date":"2022-08-12"},{"symbol":"USRT","rsi":85.7,"close":59.96,"close_date":"2022-08-12"},{"symbol":"VT","rsi":79,"close":94.35,"close_date":"2022-08-12"},{"symbol":"VTI","rsi":81.7,"close":214.94,"close_date":"2022-08-12"},{"symbol":"VXUS","rsi":69.1,"close":54.53,"close_date":"2022-08-12"}]}
