[{"date":"2023-10-24","rsi":38.77,"close":52.14,"close_target":51.62,"close_target_3":50.58,"close_target_5":49.53},{"date":"2023-10-25","rsi":33.45,"close":50.65,"close_target":50.14,"close_target_3":49.13,"close_target_5":48.12},{"date":"2023-10-26","rsi":29.79,"close":49.41,"close_target":48.92,"close_target_3":47.93,"close_target_5":46.94},{"date":"2023-10-27","rsi":28.49,"close":48.93,"close_target":48.44,"close_target_3":47.46,"close_target_5":46.48,"diff_gain_70":-20.76,"rsi_target":27.18,"rsi_target_3":24.9,"rsi_target_5":22.98}]
