[{"date":"2024-01-10","rsi":63.28,"close":237.23,"close_target":234.86,"close_target_3":230.11,"close_target_5":225.37},{"date":"2024-01-11","rsi":62.67,"close":237.07,"close_target":234.7,"close_target_3":229.96,"close_target_5":225.22},{"date":"2024-01-12","rsi":62.77,"close":237.11,"close_target":234.74,"close_target_3":230,"close_target_5":225.25},{"date":"2024-01-16","rsi":58.27,"close":236.01,"close_target":233.65,"close_target_3":228.93,"close_target_5":224.21,"diff_gain_70":-1.88,"rsi_target":50,"rsi_target_3":38.95,"rsi_target_5":31.9}]
