[{"date":"2024-09-13","rsi":58.82,"close":277.22,"close_target":274.45,"close_target_3":268.9,"close_target_5":263.36},{"date":"2024-09-16","rsi":59.59,"close":277.77,"close_target":274.99,"close_target_3":269.44,"close_target_5":263.88},{"date":"2024-09-17","rsi":60,"close":278.05,"close_target":275.27,"close_target_3":269.71,"close_target_5":264.15},{"date":"2024-09-18","rsi":58.41,"close":277.35,"close_target":274.58,"close_target_3":269.03,"close_target_5":263.48,"diff_gain_70":-1.62,"rsi_target":52.48,"rsi_target_3":43.62,"rsi_target_5":37.32}]
