[{"date":"2023-10-12","rsi":47.32,"close":214.74,"close_target":212.59,"close_target_3":208.3,"close_target_5":204},{"date":"2023-10-13","rsi":44.3,"close":213.53,"close_target":211.39,"close_target_3":207.12,"close_target_5":202.85},{"date":"2023-10-16","rsi":51.17,"close":216.01,"close_target":213.85,"close_target_3":209.53,"close_target_5":205.21},{"date":"2023-10-17","rsi":51.89,"close":216.29,"close_target":214.13,"close_target_3":209.8,"close_target_5":205.48,"diff_gain_70":-5.69,"rsi_target":46.22,"rsi_target_3":37.91,"rsi_target_5":32.15}]
